<?xml version="1.0" encoding="utf-8" ?>
<XnaContent>
  <Asset Type="_2DTowerDefenceLibraryData.Waves_Data.WaveData">
    <DisplayName>Trailer</DisplayName>
    <TextureAsset></TextureAsset>
    <EnemyNames>
      <Item>Data\GameObjects\Ships\EnemyShips\BushiHonyaki</Item>
      <Item>Data\GameObjects\Ships\EnemyShips\BushiHonyaki</Item>
      <Item>Data\GameObjects\Ships\EnemyShips\BushiHonyaki</Item>
      <Item>Data\GameObjects\Ships\EnemyShips\BushiHonyaki</Item>
      <Item>Data\GameObjects\Ships\EnemyShips\BushiHonyaki</Item>
      <Item>Data\GameObjects\Ships\EnemyShips\BushiHonyaki</Item>
      <Item>Data\GameObjects\Ships\EnemyShips\BushiTanto</Item>
      <Item>Data\GameObjects\Ships\EnemyShips\BushiTanto</Item>
      <Item>Data\GameObjects\Ships\EnemyShips\BushiTanto</Item>
      <Item>Data\GameObjects\Ships\EnemyShips\BushiTanto</Item>
    </EnemyNames>
    <SpawnPoints>
      -50 -50
      400 -100
      800 -100
      1100 -150
      1400 -150
      1700 -110
      300 1150
      800 1150
      0 400
      0 800
    </SpawnPoints>
    <TimeUntilWave>3</TimeUntilWave>
    <TimeBetweenEnemySpawns>2.5</TimeBetweenEnemySpawns>
  </Asset>
</XnaContent>
